LICENSE
MANIFEST.in
README.md
setup.py
tomasrajaolib/__init__.py
tomasrajaolib/github_api.py
tomasrajaolib.egg-info/PKG-INFO
tomasrajaolib.egg-info/SOURCES.txt
tomasrajaolib.egg-info/dependency_links.txt
tomasrajaolib.egg-info/not-zip-safe
tomasrajaolib.egg-info/requires.txt
tomasrajaolib.egg-info/top_level.txt